pyparamo-0.4.17.dist-info/METADATA
pyparamo-0.4.17.dist-info/WHEEL
pyparamo-0.4.17.dist-info/license_files/LICENSE.md
paramo/constants.py
paramo/__init__.py
paramo/conversion_funcs.py
paramo/misc_func.py
paramo/paramo.pyi
paramo/paramo.cpython-39-x86_64-linux-gnu.so
pyparamo-0.4.17.dist-info/RECORD
