Metadata-Version: 2.3
Name: pyparamo
Version: 0.4.17
Classifier: Programming Language :: Rust
Classifier: Programming Language :: Python :: Implementation :: CPython
Classifier: Programming Language :: Python :: Implementation :: PyPy
Requires-Dist: astropy >=6.0.0
Requires-Dist: matplotlib >=3.8.2
Requires-Dist: numpy >=1.26.4
Requires-Dist: pytest >=8.1.1
Requires-Dist: toml >=0.10.2
License-File: LICENSE.md
Author-email: Jesus M Rueda-Becerril <jm.ruebe@gmail.com>, Zachary Davis <zachkdavis00@gmail.com>
License: GPL-3.0-only
Requires-Python: >=3.9
